CODE_OF_CONDUCT.md
LICENSE
MANIFEST.in
README.md
setup.cfg
setup.py
conda/meta.yaml
deepblink/__init__.py
deepblink/__main__.py
deepblink/_wandb.py
deepblink/augment.py
deepblink/data.py
deepblink/inference.py
deepblink/io.py
deepblink/losses.py
deepblink/metrics.py
deepblink/optimizers.py
deepblink/training.py
deepblink/util.py
deepblink.egg-info/PKG-INFO
deepblink.egg-info/SOURCES.txt
deepblink.egg-info/dependency_links.txt
deepblink.egg-info/entry_points.txt
deepblink.egg-info/not-zip-safe
deepblink.egg-info/requires.txt
deepblink.egg-info/top_level.txt
deepblink/cli/__init__.py
deepblink/cli/_argparse.py
deepblink/cli/_check.py
deepblink/cli/_config.py
deepblink/cli/_create.py
deepblink/cli/_download.py
deepblink/cli/_logger.py
deepblink/cli/_main.py
deepblink/cli/_parseutil.py
deepblink/cli/_predict.py
deepblink/cli/_train.py
deepblink/cli/_util.py
deepblink/cli/_visualize.py
deepblink/cli/models.txt
deepblink/datasets/__init__.py
deepblink/datasets/_datasets.py
deepblink/datasets/sequence.py
deepblink/datasets/spots.py
deepblink/models/__init__.py
deepblink/models/_models.py
deepblink/models/spots.py
deepblink/networks/__init__.py
deepblink/networks/_networks.py
deepblink/networks/unet.py